Workbook
Name PlatformList: '手数料マスタ'!$A$5:$A$104

Sheet はじめに
A1: 実利益・在庫管理キット
A2: 販売の手残りと在庫の滞留を、ひとつのファイルで。
A4: 手順・項目 | B4: 使い方
A5: 1 ｜ 手数料を設定 | B5: 「手数料マスタ」で手数料率を確認・編集します。初期値は例です。契約・キャンペーン等の実際の料率を確認してください。
A6: 2 ｜ 仕入れを記録 | B6: 「販売記録」に商品名・プラットフォーム・仕入価格・仕入日を入力し、状態を「在庫」にします。
A7: 3 ｜ 売れたら更新 | B7: 販売日・販売価格・送料・梱包費を入力し、状態を「販売済み」にします。費用がない場合も 0 を入力します。
A8: 4 ｜ 利益を確認 | B8: 販売手数料＝販売価格×マスタ料率（円未満四捨五入）。利益＝販売価格－販売手数料－送料－仕入価格－梱包費。
A9: 5 ｜ 在庫を確認 | B9: 「在庫一覧」は状態が在庫の商品を自動表示します。経過日数は今日－仕入日。30日以上を色付けします。
A10: 6 ｜ 採算を検討 | B10: 「採算シミュレータ」の青いセルを変更します。手残りは仕入・送料・梱包費も差し引いた利益です。利益率＝利益÷売値。
A11: 7 ｜ 月次を確認 | B11: 「月次集計」は販売日の属する月で、販売済みの商品のみ集計します。対象年は月次集計 B2 で変更できます。
A12: 入力と計算の色 | B12: 青色セルは入力欄、薄緑色セルは数式です。数式は上書きせず、入力欄のみ編集してください。
A13: サンプル | B13: 商品A・商品B（販売済み）と商品C（在庫）を収録。使い始める前に入力欄を消去・置換してください。
A14: 継続利用・行数 | B14: 販売記録・在庫一覧は各 1,000 件分の数式を用意。空いている入力行に追記できます。
A15: 上限を超えるとき | B15: 既存データをバックアップし、付属の extend.py で入力済みファイルを別名に拡張できます。数式・集計範囲・入力規則も更新します。
... A20: Excel / Google | B20: Excelで開くか、GoogleドライブへアップロードしてGoogleスプレッドシートで開いてください。マクロ・外部リンクはありません。

Sheet 販売記録
A1: 販売記録
A2: 青＝入力 ｜ 緑＝自動計算 ｜ 1,000件分 ｜ 費用ゼロは 0 を入力 ｜ 販売日と仕入日は別に記録
A4: 販売日 | B4: 商品名 | C4: プラットフォーム | D4: 仕入価格 | E4: 販売価格 | F4: 販売手数料 | G4: 送料 | H4: 梱包費 | I4: 利益 | J4: 状態 | K4: 仕入日 | L4: 在庫連番
A5: 46296 | B5: 商品A | C5: メルカリ | D5: 2000 | E5: 5000 | F5: =IF(OR(B5="",J5<>"販売済み",E5="",C5=""),"",IFERROR(IF(OR(COUNTIF('手数料マスタ'!$A$5:$A$104,C5)<>1,COUNTIFS('手数料マスタ'!$A$5:$A$104,C5,'手数料マスタ'!$B$5:$B$104,"<>")<>1,NOT(ISNUMBER(VLOOKUP(C5,'手数料マスタ'!$A$5:$B$104,2,FALSE))),VLOOKUP(C5,'手数料マスタ'!$A$5:$B$104,2,FALSE)<0,VLOOKUP(C5,'手数料マスタ'!$A$5:$B$104,2,FALSE)>1),"要確認",ROUND(E5*VLOOKUP(C5,'手数料マスタ'!$A$5:$B$104,2,FALSE),0)),"要確認")) -> 500 | G5: 700 | H5: 100 | I5: =IF(OR(B5="",J5<>"販売済み",D5="",E5="",G5="",H5=""),"",IF(ISNUMBER(F5),E5-D5-F5-G5-H5,"要確認")) -> 1700 | J5: 販売済み | K5: 46280 | L5: =IF(AND(B5<>"",J5="在庫"),COUNTIFS($J$5:J5,"在庫",$B$5:B5,"<>"),"")
A6: 46297 | B6: 商品B | C6: メルカリ | D6: 500 | E6: 1500 | F6: =IF(OR(B6="",J6<>"販売済み",E6="",C6=""),"",IFERROR(IF(OR(COUNTIF('手数料マスタ'!$A$5:$A$104,C6)<>1,COUNTIFS('手数料マスタ'!$A$5:$A$104,C6,'手数料マスタ'!$B$5:$B$104,"<>")<>1,NOT(ISNUMBER(VLOOKUP(C6,'手数料マスタ'!$A$5:$B$104,2,FALSE))),VLOOKUP(C6,'手数料マスタ'!$A$5:$B$104,2,FALSE)<0,VLOOKUP(C6,'手数料マスタ'!$A$5:$B$104,2,FALSE)>1),"要確認",ROUND(E6*VLOOKUP(C6,'手数料マスタ'!$A$5:$B$104,2,FALSE),0)),"要確認")) -> 150 | G6: 210 | H6: 50 | I6: =IF(OR(B6="",J6<>"販売済み",D6="",E6="",G6="",H6=""),"",IF(ISNUMBER(F6),E6-D6-F6-G6-H6,"要確認")) -> 590 | J6: 販売済み | K6: 46285 | L6: =IF(AND(B6<>"",J6="在庫"),COUNTIFS($J$5:J6,"在庫",$B$5:B6,"<>"),"")
B7: 商品C | C7: メルカリ | D7: 1000 | F7: =IF(OR(B7="",J7<>"販売済み",E7="",C7=""),"",IFERROR(IF(OR(COUNTIF('手数料マスタ'!$A$5:$A$104,C7)<>1,COUNTIFS('手数料マスタ'!$A$5:$A$104,C7,'手数料マスタ'!$B$5:$B$104,"<>")<>1,NOT(ISNUMBER(VLOOKUP(C7,'手数料マスタ'!$A$5:$B$104,2,FALSE))),VLOOKUP(C7,'手数料マスタ'!$A$5:$B$104,2,FALSE)<0,VLOOKUP(C7,'手数料マスタ'!$A$5:$B$104,2,FALSE)>1),"要確認",ROUND(E7*VLOOKUP(C7,'手数料マスタ'!$A$5:$B$104,2,FALSE),0)),"要確認")) | I7: =IF(OR(B7="",J7<>"販売済み",D7="",E7="",G7="",H7=""),"",IF(ISNUMBER(F7),E7-D7-F7-G7-H7,"要確認")) | J7: 在庫 | K7: 46266 | L7: =IF(AND(B7<>"",J7="在庫"),COUNTIFS($J$5:J7,"在庫",$B$5:B7,"<>"),"") -> 1
F8: =IF(OR(B8="",J8<>"販売済み",E8="",C8=""),"",IFERROR(IF(OR(COUNTIF('手数料マスタ'!$A$5:$A$104,C8)<>1,COUNTIFS('手数料マスタ'!$A$5:$A$104,C8,'手数料マスタ'!$B$5:$B$104,"<>")<>1,NOT(ISNUMBER(VLOOKUP(C8,'手数料マスタ'!$A$5:$B$104,2,FALSE))),VLOOKUP(C8,'手数料マスタ'!$A$5:$B$104,2,FALSE)<0,VLOOKUP(C8,'手数料マスタ'!$A$5:$B$104,2,FALSE)>1),"要確認",ROUND(E8*VLOOKUP(C8,'手数料マスタ'!$A$5:$B$104,2,FALSE),0)),"要確認")) | I8: =IF(OR(B8="",J8<>"販売済み",D8="",E8="",G8="",H8=""),"",IF(ISNUMBER(F8),E8-D8-F8-G8-H8,"要確認")) | L8: =IF(AND(B8<>"",J8="在庫"),COUNTIFS($J$5:J8,"在庫",$B$5:B8,"<>"),"")
F9: =IF(OR(B9="",J9<>"販売済み",E9="",C9=""),"",IFERROR(IF(OR(COUNTIF('手数料マスタ'!$A$5:$A$104,C9)<>1,COUNTIFS('手数料マスタ'!$A$5:$A$104,C9,'手数料マスタ'!$B$5:$B$104,"<>")<>1,NOT(ISNUMBER(VLOOKUP(C9,'手数料マスタ'!$A$5:$B$104,2,FALSE))),VLOOKUP(C9,'手数料マスタ'!$A$5:$B$104,2,FALSE)<0,VLOOKUP(C9,'手数料マスタ'!$A$5:$B$104,2,FALSE)>1),"要確認",ROUND(E9*VLOOKUP(C9,'手数料マスタ'!$A$5:$B$104,2,FALSE),0)),"要確認")) | I9: =IF(OR(B9="",J9<>"販売済み",D9="",E9="",G9="",H9=""),"",IF(ISNUMBER(F9),E9-D9-F9-G9-H9,"要確認")) | L9: =IF(AND(B9<>"",J9="在庫"),COUNTIFS($J$5:J9,"在庫",$B$5:B9,"<>"),"")
F10: =IF(OR(B10="",J10<>"販売済み",E10="",C10=""),"",IFERROR(IF(OR(COUNTIF('手数料マスタ'!$A$5:$A$104,C10)<>1,COUNTIFS('手数料マスタ'!$A$5:$A$104,C10,'手数料マスタ'!$B$5:$B$104,"<>")<>1,NOT(ISNUMBER(VLOOKUP(C10,'手数料マスタ'!$A$5:$B$104,2,FALSE))),VLOOKUP(C10,'手数料マスタ'!$A$5:$B$104,2,FALSE)<0,VLOOKUP(C10,'手数料マスタ'!$A$5:$B$104,2,FALSE)>1),"要確認",ROUND(E10*VLOOKUP(C10,'手数料マスタ'!$A$5:$B$104,2,FALSE),0)),"要確認")) | I10: =IF(OR(B10="",J10<>"販売済み",D10="",E10="",G10="",H10=""),"",IF(ISNUMBER(F10),E10-D10-F10-G10-H10,"要確認")) | L10: =IF(AND(B10<>"",J10="在庫"),COUNTIFS($J$5:J10,"在庫",$B$5:B10,"<>"),"")
F11: =IF(OR(B11="",J11<>"販売済み",E11="",C11=""),"",IFERROR(IF(OR(COUNTIF('手数料マスタ'!$A$5:$A$104,C11)<>1,COUNTIFS('手数料マスタ'!$A$5:$A$104,C11,'手数料マスタ'!$B$5:$B$104,"<>")<>1,NOT(ISNUMBER(VLOOKUP(C11,'手数料マスタ'!$A$5:$B$104,2,FALSE))),VLOOKUP(C11,'手数料マスタ'!$A$5:$B$104,2,FALSE)<0,VLOOKUP(C11,'手数料マスタ'!$A$5:$B$104,2,FALSE)>1),"要確認",ROUND(E11*VLOOKUP(C11,'手数料マスタ'!$A$5:$B$104,2,FALSE),0)),"要確認")) | I11: =IF(OR(B11="",J11<>"販売済み",D11="",E11="",G11="",H11=""),"",IF(ISNUMBER(F11),E11-D11-F11-G11-H11,"要確認")) | L11: =IF(AND(B11<>"",J11="在庫"),COUNTIFS($J$5:J11,"在庫",$B$5:B11,"<>"),"")
F12: =IF(OR(B12="",J12<>"販売済み",E12="",C12=""),"",IFERROR(IF(OR(COUNTIF('手数料マスタ'!$A$5:$A$104,C12)<>1,COUNTIFS('手数料マスタ'!$A$5:$A$104,C12,'手数料マスタ'!$B$5:$B$104,"<>")<>1,NOT(ISNUMBER(VLOOKUP(C12,'手数料マスタ'!$A$5:$B$104,2,FALSE))),VLOOKUP(C12,'手数料マスタ'!$A$5:$B$104,2,FALSE)<0,VLOOKUP(C12,'手数料マスタ'!$A$5:$B$104,2,FALSE)>1),"要確認",ROUND(E12*VLOOKUP(C12,'手数料マスタ'!$A$5:$B$104,2,FALSE),0)),"要確認")) | I12: =IF(OR(B12="",J12<>"販売済み",D12="",E12="",G12="",H12=""),"",IF(ISNUMBER(F12),E12-D12-F12-G12-H12,"要確認")) | L12: =IF(AND(B12<>"",J12="在庫"),COUNTIFS($J$5:J12,"在庫",$B$5:B12,"<>"),"")
F13: =IF(OR(B13="",J13<>"販売済み",E13="",C13=""),"",IFERROR(IF(OR(COUNTIF('手数料マスタ'!$A$5:$A$104,C13)<>1,COUNTIFS('手数料マスタ'!$A$5:$A$104,C13,'手数料マスタ'!$B$5:$B$104,"<>")<>1,NOT(ISNUMBER(VLOOKUP(C13,'手数料マスタ'!$A$5:$B$104,2,FALSE))),VLOOKUP(C13,'手数料マスタ'!$A$5:$B$104,2,FALSE)<0,VLOOKUP(C13,'手数料マスタ'!$A$5:$B$104,2,FALSE)>1),"要確認",ROUND(E13*VLOOKUP(C13,'手数料マスタ'!$A$5:$B$104,2,FALSE),0)),"要確認")) | I13: =IF(OR(B13="",J13<>"販売済み",D13="",E13="",G13="",H13=""),"",IF(ISNUMBER(F13),E13-D13-F13-G13-H13,"要確認")) | L13: =IF(AND(B13<>"",J13="在庫"),COUNTIFS($J$5:J13,"在庫",$B$5:B13,"<>"),"")
F14: =IF(OR(B14="",J14<>"販売済み",E14="",C14=""),"",IFERROR(IF(OR(COUNTIF('手数料マスタ'!$A$5:$A$104,C14)<>1,COUNTIFS('手数料マスタ'!$A$5:$A$104,C14,'手数料マスタ'!$B$5:$B$104,"<>")<>1,NOT(ISNUMBER(VLOOKUP(C14,'手数料マスタ'!$A$5:$B$104,2,FALSE))),VLOOKUP(C14,'手数料マスタ'!$A$5:$B$104,2,FALSE)<0,VLOOKUP(C14,'手数料マスタ'!$A$5:$B$104,2,FALSE)>1),"要確認",ROUND(E14*VLOOKUP(C14,'手数料マスタ'!$A$5:$B$104,2,FALSE),0)),"要確認")) | I14: =IF(OR(B14="",J14<>"販売済み",D14="",E14="",G14="",H14=""),"",IF(ISNUMBER(F14),E14-D14-F14-G14-H14,"要確認")) | L14: =IF(AND(B14<>"",J14="在庫"),COUNTIFS($J$5:J14,"在庫",$B$5:B14,"<>"),"")
F15: =IF(OR(B15="",J15<>"販売済み",E15="",C15=""),"",IFERROR(IF(OR(COUNTIF('手数料マスタ'!$A$5:$A$104,C15)<>1,COUNTIFS('手数料マスタ'!$A$5:$A$104,C15,'手数料マスタ'!$B$5:$B$104,"<>")<>1,NOT(ISNUMBER(VLOOKUP(C15,'手数料マスタ'!$A$5:$B$104,2,FALSE))),VLOOKUP(C15,'手数料マスタ'!$A$5:$B$104,2,FALSE)<0,VLOOKUP(C15,'手数料マスタ'!$A$5:$B$104,2,FALSE)>1),"要確認",ROUND(E15*VLOOKUP(C15,'手数料マスタ'!$A$5:$B$104,2,FALSE),0)),"要確認")) | I15: =IF(OR(B15="",J15<>"販売済み",D15="",E15="",G15="",H15=""),"",IF(ISNUMBER(F15),E15-D15-F15-G15-H15,"要確認")) | L15: =IF(AND(B15<>"",J15="在庫"),COUNTIFS($J$5:J15,"在庫",$B$5:B15,"<>"),"")
F16: =IF(OR(B16="",J16<>"販売済み",E16="",C16=""),"",IFERROR(IF(OR(COUNTIF('手数料マスタ'!$A$5:$A$104,C16)<>1,COUNTIFS('手数料マスタ'!$A$5:$A$104,C16,'手数料マスタ'!$B$5:$B$104,"<>")<>1,NOT(ISNUMBER(VLOOKUP(C16,'手数料マスタ'!$A$5:$B$104,2,FALSE))),VLOOKUP(C16,'手数料マスタ'!$A$5:$B$104,2,FALSE)<0,VLOOKUP(C16,'手数料マスタ'!$A$5:$B$104,2,FALSE)>1),"要確認",ROUND(E16*VLOOKUP(C16,'手数料マスタ'!$A$5:$B$104,2,FALSE),0)),"要確認")) | I16: =IF(OR(B16="",J16<>"販売済み",D16="",E16="",G16="",H16=""),"",IF(ISNUMBER(F16),E16-D16-F16-G16-H16,"要確認")) | L16: =IF(AND(B16<>"",J16="在庫"),COUNTIFS($J$5:J16,"在庫",$B$5:B16,"<>"),"")
F17: =IF(OR(B17="",J17<>"販売済み",E17="",C17=""),"",IFERROR(IF(OR(COUNTIF('手数料マスタ'!$A$5:$A$104,C17)<>1,COUNTIFS('手数料マスタ'!$A$5:$A$104,C17,'手数料マスタ'!$B$5:$B$104,"<>")<>1,NOT(ISNUMBER(VLOOKUP(C17,'手数料マスタ'!$A$5:$B$104,2,FALSE))),VLOOKUP(C17,'手数料マスタ'!$A$5:$B$104,2,FALSE)<0,VLOOKUP(C17,'手数料マスタ'!$A$5:$B$104,2,FALSE)>1),"要確認",ROUND(E17*VLOOKUP(C17,'手数料マスタ'!$A$5:$B$104,2,FALSE),0)),"要確認")) | I17: =IF(OR(B17="",J17<>"販売済み",D17="",E17="",G17="",H17=""),"",IF(ISNUMBER(F17),E17-D17-F17-G17-H17,"要確認")) | L17: =IF(AND(B17<>"",J17="在庫"),COUNTIFS($J$5:J17,"在庫",$B$5:B17,"<>"),"")
F18: =IF(OR(B18="",J18<>"販売済み",E18="",C18=""),"",IFERROR(IF(OR(COUNTIF('手数料マスタ'!$A$5:$A$104,C18)<>1,COUNTIFS('手数料マスタ'!$A$5:$A$104,C18,'手数料マスタ'!$B$5:$B$104,"<>")<>1,NOT(ISNUMBER(VLOOKUP(C18,'手数料マスタ'!$A$5:$B$104,2,FALSE))),VLOOKUP(C18,'手数料マスタ'!$A$5:$B$104,2,FALSE)<0,VLOOKUP(C18,'手数料マスタ'!$A$5:$B$104,2,FALSE)>1),"要確認",ROUND(E18*VLOOKUP(C18,'手数料マスタ'!$A$5:$B$104,2,FALSE),0)),"要確認")) | I18: =IF(OR(B18="",J18<>"販売済み",D18="",E18="",G18="",H18=""),"",IF(ISNUMBER(F18),E18-D18-F18-G18-H18,"要確認")) | L18: =IF(AND(B18<>"",J18="在庫"),COUNTIFS($J$5:J18,"在庫",$B$5:B18,"<>"),"")
F19: =IF(OR(B19="",J19<>"販売済み",E19="",C19=""),"",IFERROR(IF(OR(COUNTIF('手数料マスタ'!$A$5:$A$104,C19)<>1,COUNTIFS('手数料マスタ'!$A$5:$A$104,C19,'手数料マスタ'!$B$5:$B$104,"<>")<>1,NOT(ISNUMBER(VLOOKUP(C19,'手数料マスタ'!$A$5:$B$104,2,FALSE))),VLOOKUP(C19,'手数料マスタ'!$A$5:$B$104,2,FALSE)<0,VLOOKUP(C19,'手数料マスタ'!$A$5:$B$104,2,FALSE)>1),"要確認",ROUND(E19*VLOOKUP(C19,'手数料マスタ'!$A$5:$B$104,2,FALSE),0)),"要確認")) | I19: =IF(OR(B19="",J19<>"販売済み",D19="",E19="",G19="",H19=""),"",IF(ISNUMBER(F19),E19-D19-F19-G19-H19,"要確認")) | L19: =IF(AND(B19<>"",J19="在庫"),COUNTIFS($J$5:J19,"在庫",$B$5:B19,"<>"),"")
... F1004: =IF(OR(B1004="",J1004<>"販売済み",E1004="",C1004=""),"",IFERROR(IF(OR(COUNTIF('手数料マスタ'!$A$5:$A$104,C1004)<>1,COUNTIFS('手数料マスタ'!$A$5:$A$104,C1004,'手数料マスタ'!$B$5:$B$104,"<>")<>1,NOT(ISNUMBER(VLOOKUP(C1004,'手数料マスタ'!$A$5:$B$104,2,FALSE))),VLOOKUP(C1004,'手数料マスタ'!$A$5:$B$104,2,FALSE)<0,VLOOKUP(C1004,'手数料マスタ'!$A$5:$B$104,2,FALSE)>1),"要確認",ROUND(E1004*VLOOKUP(C1004,'手数料マスタ'!$A$5:$B$104,2,FALSE),0)),"要確認")) | I1004: =IF(OR(B1004="",J1004<>"販売済み",D1004="",E1004="",G1004="",H1004=""),"",IF(ISNUMBER(F1004),E1004-D1004-F1004-G1004-H1004,"要確認")) | L1004: =IF(AND(B1004<>"",J1004="在庫"),COUNTIFS($J$5:J1004,"在庫",$B$5:B1004,"<>"),"")

Sheet 手数料マスタ
A1: 手数料マスタ
A2: 編集可能な参考値です。実際の契約・最新の料率を確認してください。変更は過去分にも反映されます。
A4: プラットフォーム | B4: 手数料率 | C4: 備考
A5: メルカリ | B5: 0.1 | C5: 参考初期値。販売価格に対する割合。
A6: Yahoo!フリマ | B6: 0.05 | C6: 参考例。キャンペーン等による変更を確認。
A7: その他 | B7: 0.1 | C7: 仮の料率。利用サービスに合わせて編集。

Sheet 在庫一覧
A1: 在庫一覧
A2: 販売記録の「在庫」を自動表示 ｜ 経過30日以上は要チェック ｜ 販売記録の入力欄で更新します
A4: 仕入日 | B4: 商品名 | C4: プラットフォーム | D4: 仕入価格 | E4: 経過日数 | F4: 参照行
A5: =IF($F5="","",IF(INDEX('販売記録'!$K$5:$K$1004,$F5)="","",INDEX('販売記録'!$K$5:$K$1004,$F5))) -> 46266 | B5: =IF($F5="","",IF(INDEX('販売記録'!$B$5:$B$1004,$F5)="","",INDEX('販売記録'!$B$5:$B$1004,$F5))) -> 商品C | C5: =IF($F5="","",IF(INDEX('販売記録'!$C$5:$C$1004,$F5)="","",INDEX('販売記録'!$C$5:$C$1004,$F5))) -> メルカリ | D5: =IF($F5="","",IF(INDEX('販売記録'!$D$5:$D$1004,$F5)="","",INDEX('販売記録'!$D$5:$D$1004,$F5))) -> 1000 | E5: =IF(OR(A5="",B5=""),"",MAX(0,TODAY()-A5)) -> 56 | F5: =IFERROR(MATCH(ROW()-4,'販売記録'!$L$5:$L$1004,0),"") -> 3
A6: =IF($F6="","",IF(INDEX('販売記録'!$K$5:$K$1004,$F6)="","",INDEX('販売記録'!$K$5:$K$1004,$F6))) | B6: =IF($F6="","",IF(INDEX('販売記録'!$B$5:$B$1004,$F6)="","",INDEX('販売記録'!$B$5:$B$1004,$F6))) | C6: =IF($F6="","",IF(INDEX('販売記録'!$C$5:$C$1004,$F6)="","",INDEX('販売記録'!$C$5:$C$1004,$F6))) | D6: =IF($F6="","",IF(INDEX('販売記録'!$D$5:$D$1004,$F6)="","",INDEX('販売記録'!$D$5:$D$1004,$F6))) | E6: =IF(OR(A6="",B6=""),"",MAX(0,TODAY()-A6)) | F6: =IFERROR(MATCH(ROW()-4,'販売記録'!$L$5:$L$1004,0),"")
A7: =IF($F7="","",IF(INDEX('販売記録'!$K$5:$K$1004,$F7)="","",INDEX('販売記録'!$K$5:$K$1004,$F7))) | B7: =IF($F7="","",IF(INDEX('販売記録'!$B$5:$B$1004,$F7)="","",INDEX('販売記録'!$B$5:$B$1004,$F7))) | C7: =IF($F7="","",IF(INDEX('販売記録'!$C$5:$C$1004,$F7)="","",INDEX('販売記録'!$C$5:$C$1004,$F7))) | D7: =IF($F7="","",IF(INDEX('販売記録'!$D$5:$D$1004,$F7)="","",INDEX('販売記録'!$D$5:$D$1004,$F7))) | E7: =IF(OR(A7="",B7=""),"",MAX(0,TODAY()-A7)) | F7: =IFERROR(MATCH(ROW()-4,'販売記録'!$L$5:$L$1004,0),"")
A8: =IF($F8="","",IF(INDEX('販売記録'!$K$5:$K$1004,$F8)="","",INDEX('販売記録'!$K$5:$K$1004,$F8))) | B8: =IF($F8="","",IF(INDEX('販売記録'!$B$5:$B$1004,$F8)="","",INDEX('販売記録'!$B$5:$B$1004,$F8))) | C8: =IF($F8="","",IF(INDEX('販売記録'!$C$5:$C$1004,$F8)="","",INDEX('販売記録'!$C$5:$C$1004,$F8))) | D8: =IF($F8="","",IF(INDEX('販売記録'!$D$5:$D$1004,$F8)="","",INDEX('販売記録'!$D$5:$D$1004,$F8))) | E8: =IF(OR(A8="",B8=""),"",MAX(0,TODAY()-A8)) | F8: =IFERROR(MATCH(ROW()-4,'販売記録'!$L$5:$L$1004,0),"")
A9: =IF($F9="","",IF(INDEX('販売記録'!$K$5:$K$1004,$F9)="","",INDEX('販売記録'!$K$5:$K$1004,$F9))) | B9: =IF($F9="","",IF(INDEX('販売記録'!$B$5:$B$1004,$F9)="","",INDEX('販売記録'!$B$5:$B$1004,$F9))) | C9: =IF($F9="","",IF(INDEX('販売記録'!$C$5:$C$1004,$F9)="","",INDEX('販売記録'!$C$5:$C$1004,$F9))) | D9: =IF($F9="","",IF(INDEX('販売記録'!$D$5:$D$1004,$F9)="","",INDEX('販売記録'!$D$5:$D$1004,$F9))) | E9: =IF(OR(A9="",B9=""),"",MAX(0,TODAY()-A9)) | F9: =IFERROR(MATCH(ROW()-4,'販売記録'!$L$5:$L$1004,0),"")
A10: =IF($F10="","",IF(INDEX('販売記録'!$K$5:$K$1004,$F10)="","",INDEX('販売記録'!$K$5:$K$1004,$F10))) | B10: =IF($F10="","",IF(INDEX('販売記録'!$B$5:$B$1004,$F10)="","",INDEX('販売記録'!$B$5:$B$1004,$F10))) | C10: =IF($F10="","",IF(INDEX('販売記録'!$C$5:$C$1004,$F10)="","",INDEX('販売記録'!$C$5:$C$1004,$F10))) | D10: =IF($F10="","",IF(INDEX('販売記録'!$D$5:$D$1004,$F10)="","",INDEX('販売記録'!$D$5:$D$1004,$F10))) | E10: =IF(OR(A10="",B10=""),"",MAX(0,TODAY()-A10)) | F10: =IFERROR(MATCH(ROW()-4,'販売記録'!$L$5:$L$1004,0),"")
A11: =IF($F11="","",IF(INDEX('販売記録'!$K$5:$K$1004,$F11)="","",INDEX('販売記録'!$K$5:$K$1004,$F11))) | B11: =IF($F11="","",IF(INDEX('販売記録'!$B$5:$B$1004,$F11)="","",INDEX('販売記録'!$B$5:$B$1004,$F11))) | C11: =IF($F11="","",IF(INDEX('販売記録'!$C$5:$C$1004,$F11)="","",INDEX('販売記録'!$C$5:$C$1004,$F11))) | D11: =IF($F11="","",IF(INDEX('販売記録'!$D$5:$D$1004,$F11)="","",INDEX('販売記録'!$D$5:$D$1004,$F11))) | E11: =IF(OR(A11="",B11=""),"",MAX(0,TODAY()-A11)) | F11: =IFERROR(MATCH(ROW()-4,'販売記録'!$L$5:$L$1004,0),"")
A12: =IF($F12="","",IF(INDEX('販売記録'!$K$5:$K$1004,$F12)="","",INDEX('販売記録'!$K$5:$K$1004,$F12))) | B12: =IF($F12="","",IF(INDEX('販売記録'!$B$5:$B$1004,$F12)="","",INDEX('販売記録'!$B$5:$B$1004,$F12))) | C12: =IF($F12="","",IF(INDEX('販売記録'!$C$5:$C$1004,$F12)="","",INDEX('販売記録'!$C$5:$C$1004,$F12))) | D12: =IF($F12="","",IF(INDEX('販売記録'!$D$5:$D$1004,$F12)="","",INDEX('販売記録'!$D$5:$D$1004,$F12))) | E12: =IF(OR(A12="",B12=""),"",MAX(0,TODAY()-A12)) | F12: =IFERROR(MATCH(ROW()-4,'販売記録'!$L$5:$L$1004,0),"")
A13: =IF($F13="","",IF(INDEX('販売記録'!$K$5:$K$1004,$F13)="","",INDEX('販売記録'!$K$5:$K$1004,$F13))) | B13: =IF($F13="","",IF(INDEX('販売記録'!$B$5:$B$1004,$F13)="","",INDEX('販売記録'!$B$5:$B$1004,$F13))) | C13: =IF($F13="","",IF(INDEX('販売記録'!$C$5:$C$1004,$F13)="","",INDEX('販売記録'!$C$5:$C$1004,$F13))) | D13: =IF($F13="","",IF(INDEX('販売記録'!$D$5:$D$1004,$F13)="","",INDEX('販売記録'!$D$5:$D$1004,$F13))) | E13: =IF(OR(A13="",B13=""),"",MAX(0,TODAY()-A13)) | F13: =IFERROR(MATCH(ROW()-4,'販売記録'!$L$5:$L$1004,0),"")
A14: =IF($F14="","",IF(INDEX('販売記録'!$K$5:$K$1004,$F14)="","",INDEX('販売記録'!$K$5:$K$1004,$F14))) | B14: =IF($F14="","",IF(INDEX('販売記録'!$B$5:$B$1004,$F14)="","",INDEX('販売記録'!$B$5:$B$1004,$F14))) | C14: =IF($F14="","",IF(INDEX('販売記録'!$C$5:$C$1004,$F14)="","",INDEX('販売記録'!$C$5:$C$1004,$F14))) | D14: =IF($F14="","",IF(INDEX('販売記録'!$D$5:$D$1004,$F14)="","",INDEX('販売記録'!$D$5:$D$1004,$F14))) | E14: =IF(OR(A14="",B14=""),"",MAX(0,TODAY()-A14)) | F14: =IFERROR(MATCH(ROW()-4,'販売記録'!$L$5:$L$1004,0),"")
A15: =IF($F15="","",IF(INDEX('販売記録'!$K$5:$K$1004,$F15)="","",INDEX('販売記録'!$K$5:$K$1004,$F15))) | B15: =IF($F15="","",IF(INDEX('販売記録'!$B$5:$B$1004,$F15)="","",INDEX('販売記録'!$B$5:$B$1004,$F15))) | C15: =IF($F15="","",IF(INDEX('販売記録'!$C$5:$C$1004,$F15)="","",INDEX('販売記録'!$C$5:$C$1004,$F15))) | D15: =IF($F15="","",IF(INDEX('販売記録'!$D$5:$D$1004,$F15)="","",INDEX('販売記録'!$D$5:$D$1004,$F15))) | E15: =IF(OR(A15="",B15=""),"",MAX(0,TODAY()-A15)) | F15: =IFERROR(MATCH(ROW()-4,'販売記録'!$L$5:$L$1004,0),"")
A16: =IF($F16="","",IF(INDEX('販売記録'!$K$5:$K$1004,$F16)="","",INDEX('販売記録'!$K$5:$K$1004,$F16))) | B16: =IF($F16="","",IF(INDEX('販売記録'!$B$5:$B$1004,$F16)="","",INDEX('販売記録'!$B$5:$B$1004,$F16))) | C16: =IF($F16="","",IF(INDEX('販売記録'!$C$5:$C$1004,$F16)="","",INDEX('販売記録'!$C$5:$C$1004,$F16))) | D16: =IF($F16="","",IF(INDEX('販売記録'!$D$5:$D$1004,$F16)="","",INDEX('販売記録'!$D$5:$D$1004,$F16))) | E16: =IF(OR(A16="",B16=""),"",MAX(0,TODAY()-A16)) | F16: =IFERROR(MATCH(ROW()-4,'販売記録'!$L$5:$L$1004,0),"")
... A1004: =IF($F1004="","",IF(INDEX('販売記録'!$K$5:$K$1004,$F1004)="","",INDEX('販売記録'!$K$5:$K$1004,$F1004))) | B1004: =IF($F1004="","",IF(INDEX('販売記録'!$B$5:$B$1004,$F1004)="","",INDEX('販売記録'!$B$5:$B$1004,$F1004))) | C1004: =IF($F1004="","",IF(INDEX('販売記録'!$C$5:$C$1004,$F1004)="","",INDEX('販売記録'!$C$5:$C$1004,$F1004))) | D1004: =IF($F1004="","",IF(INDEX('販売記録'!$D$5:$D$1004,$F1004)="","",INDEX('販売記録'!$D$5:$D$1004,$F1004))) | E1004: =IF(OR(A1004="",B1004=""),"",MAX(0,TODAY()-A1004)) | F1004: =IFERROR(MATCH(ROW()-4,'販売記録'!$L$5:$L$1004,0),"")

Sheet 採算シミュレータ
A1: 採算シミュレータ
A2: 青いセルを変更して採算を確認 ｜ 手残りは全入力費用を引いた利益 ｜ 料率は直接入力
A4: 項目 | B4: 金額・割合 | C4: 説明
A5: 売値 | B5: 3000
A6: 仕入 | B6: 1200
A7: 送料 | B7: 520
A8: 梱包費 | B8: 80
A9: 手数料率 | B9: 0.1
A11: 販売手数料 | B11: =IF(COUNT(B5:B9)<5,"",ROUND(B5*B9,0)) -> 300 | C11: 売値×手数料率。円未満四捨五入。
A12: 手残り | B12: =IF(COUNT(B5:B9)<5,"",B5-SUM(B6:B8)-B11) -> 900 | C12: 売値－仕入－送料－梱包費－販売手数料。
A13: 利益率 | B13: =IF(OR(COUNT(B5:B9)<5,B5=0),"",B12/B5) -> 0.3 | C13: 手残り÷売値。売値ゼロの場合は空欄。
A14: 損益分岐売値 | B14: =IF(COUNT(B6:B9)<4,"",IF(B9>=1,"算出不可",ROUNDUP(SUM(B6:B8)/(1-B9),0))) -> 2000 | C14: 手数料の端数丸め前の費用回収目安（円単位切上げ）。料率100%は算出不可。

Sheet 月次集計
A1: 月次集計
A2: 対象年 | B2: 2026 | C2: 販売済みのみ・販売日基準。未入力の費用がないか販売記録も確認してください。
A4: 月 | B4: 売上 | C4: 手数料 | D4: 送料 | E4: 仕入 | F4: 梱包費 | G4: 利益
A5: =DATE($B$2,1,1) -> 46023 | B5: =SUMIFS('販売記録'!$E$5:$E$1004,'販売記録'!$J$5:$J$1004,"販売済み",'販売記録'!$A$5:$A$1004,">="&$A5,'販売記録'!$A$5:$A$1004,"<"&DATE(YEAR($A5),MONTH($A5)+1,1)) -> 0 | C5: =SUMIFS('販売記録'!$F$5:$F$1004,'販売記録'!$J$5:$J$1004,"販売済み",'販売記録'!$A$5:$A$1004,">="&$A5,'販売記録'!$A$5:$A$1004,"<"&DATE(YEAR($A5),MONTH($A5)+1,1)) -> 0 | D5: =SUMIFS('販売記録'!$G$5:$G$1004,'販売記録'!$J$5:$J$1004,"販売済み",'販売記録'!$A$5:$A$1004,">="&$A5,'販売記録'!$A$5:$A$1004,"<"&DATE(YEAR($A5),MONTH($A5)+1,1)) -> 0 | E5: =SUMIFS('販売記録'!$D$5:$D$1004,'販売記録'!$J$5:$J$1004,"販売済み",'販売記録'!$A$5:$A$1004,">="&$A5,'販売記録'!$A$5:$A$1004,"<"&DATE(YEAR($A5),MONTH($A5)+1,1)) -> 0 | F5: =SUMIFS('販売記録'!$H$5:$H$1004,'販売記録'!$J$5:$J$1004,"販売済み",'販売記録'!$A$5:$A$1004,">="&$A5,'販売記録'!$A$5:$A$1004,"<"&DATE(YEAR($A5),MONTH($A5)+1,1)) -> 0 | G5: =SUMIFS('販売記録'!$I$5:$I$1004,'販売記録'!$J$5:$J$1004,"販売済み",'販売記録'!$A$5:$A$1004,">="&$A5,'販売記録'!$A$5:$A$1004,"<"&DATE(YEAR($A5),MONTH($A5)+1,1)) -> 0
A6: =DATE($B$2,2,1) -> 46054 | B6: =SUMIFS('販売記録'!$E$5:$E$1004,'販売記録'!$J$5:$J$1004,"販売済み",'販売記録'!$A$5:$A$1004,">="&$A6,'販売記録'!$A$5:$A$1004,"<"&DATE(YEAR($A6),MONTH($A6)+1,1)) -> 0 | C6: =SUMIFS('販売記録'!$F$5:$F$1004,'販売記録'!$J$5:$J$1004,"販売済み",'販売記録'!$A$5:$A$1004,">="&$A6,'販売記録'!$A$5:$A$1004,"<"&DATE(YEAR($A6),MONTH($A6)+1,1)) -> 0 | D6: =SUMIFS('販売記録'!$G$5:$G$1004,'販売記録'!$J$5:$J$1004,"販売済み",'販売記録'!$A$5:$A$1004,">="&$A6,'販売記録'!$A$5:$A$1004,"<"&DATE(YEAR($A6),MONTH($A6)+1,1)) -> 0 | E6: =SUMIFS('販売記録'!$D$5:$D$1004,'販売記録'!$J$5:$J$1004,"販売済み",'販売記録'!$A$5:$A$1004,">="&$A6,'販売記録'!$A$5:$A$1004,"<"&DATE(YEAR($A6),MONTH($A6)+1,1)) -> 0 | F6: =SUMIFS('販売記録'!$H$5:$H$1004,'販売記録'!$J$5:$J$1004,"販売済み",'販売記録'!$A$5:$A$1004,">="&$A6,'販売記録'!$A$5:$A$1004,"<"&DATE(YEAR($A6),MONTH($A6)+1,1)) -> 0 | G6: =SUMIFS('販売記録'!$I$5:$I$1004,'販売記録'!$J$5:$J$1004,"販売済み",'販売記録'!$A$5:$A$1004,">="&$A6,'販売記録'!$A$5:$A$1004,"<"&DATE(YEAR($A6),MONTH($A6)+1,1)) -> 0
A7: =DATE($B$2,3,1) -> 46082 | B7: =SUMIFS('販売記録'!$E$5:$E$1004,'販売記録'!$J$5:$J$1004,"販売済み",'販売記録'!$A$5:$A$1004,">="&$A7,'販売記録'!$A$5:$A$1004,"<"&DATE(YEAR($A7),MONTH($A7)+1,1)) -> 0 | C7: =SUMIFS('販売記録'!$F$5:$F$1004,'販売記録'!$J$5:$J$1004,"販売済み",'販売記録'!$A$5:$A$1004,">="&$A7,'販売記録'!$A$5:$A$1004,"<"&DATE(YEAR($A7),MONTH($A7)+1,1)) -> 0 | D7: =SUMIFS('販売記録'!$G$5:$G$1004,'販売記録'!$J$5:$J$1004,"販売済み",'販売記録'!$A$5:$A$1004,">="&$A7,'販売記録'!$A$5:$A$1004,"<"&DATE(YEAR($A7),MONTH($A7)+1,1)) -> 0 | E7: =SUMIFS('販売記録'!$D$5:$D$1004,'販売記録'!$J$5:$J$1004,"販売済み",'販売記録'!$A$5:$A$1004,">="&$A7,'販売記録'!$A$5:$A$1004,"<"&DATE(YEAR($A7),MONTH($A7)+1,1)) -> 0 | F7: =SUMIFS('販売記録'!$H$5:$H$1004,'販売記録'!$J$5:$J$1004,"販売済み",'販売記録'!$A$5:$A$1004,">="&$A7,'販売記録'!$A$5:$A$1004,"<"&DATE(YEAR($A7),MONTH($A7)+1,1)) -> 0 | G7: =SUMIFS('販売記録'!$I$5:$I$1004,'販売記録'!$J$5:$J$1004,"販売済み",'販売記録'!$A$5:$A$1004,">="&$A7,'販売記録'!$A$5:$A$1004,"<"&DATE(YEAR($A7),MONTH($A7)+1,1)) -> 0
A8: =DATE($B$2,4,1) -> 46113 | B8: =SUMIFS('販売記録'!$E$5:$E$1004,'販売記録'!$J$5:$J$1004,"販売済み",'販売記録'!$A$5:$A$1004,">="&$A8,'販売記録'!$A$5:$A$1004,"<"&DATE(YEAR($A8),MONTH($A8)+1,1)) -> 0 | C8: =SUMIFS('販売記録'!$F$5:$F$1004,'販売記録'!$J$5:$J$1004,"販売済み",'販売記録'!$A$5:$A$1004,">="&$A8,'販売記録'!$A$5:$A$1004,"<"&DATE(YEAR($A8),MONTH($A8)+1,1)) -> 0 | D8: =SUMIFS('販売記録'!$G$5:$G$1004,'販売記録'!$J$5:$J$1004,"販売済み",'販売記録'!$A$5:$A$1004,">="&$A8,'販売記録'!$A$5:$A$1004,"<"&DATE(YEAR($A8),MONTH($A8)+1,1)) -> 0 | E8: =SUMIFS('販売記録'!$D$5:$D$1004,'販売記録'!$J$5:$J$1004,"販売済み",'販売記録'!$A$5:$A$1004,">="&$A8,'販売記録'!$A$5:$A$1004,"<"&DATE(YEAR($A8),MONTH($A8)+1,1)) -> 0 | F8: =SUMIFS('販売記録'!$H$5:$H$1004,'販売記録'!$J$5:$J$1004,"販売済み",'販売記録'!$A$5:$A$1004,">="&$A8,'販売記録'!$A$5:$A$1004,"<"&DATE(YEAR($A8),MONTH($A8)+1,1)) -> 0 | G8: =SUMIFS('販売記録'!$I$5:$I$1004,'販売記録'!$J$5:$J$1004,"販売済み",'販売記録'!$A$5:$A$1004,">="&$A8,'販売記録'!$A$5:$A$1004,"<"&DATE(YEAR($A8),MONTH($A8)+1,1)) -> 0
A9: =DATE($B$2,5,1) -> 46143 | B9: =SUMIFS('販売記録'!$E$5:$E$1004,'販売記録'!$J$5:$J$1004,"販売済み",'販売記録'!$A$5:$A$1004,">="&$A9,'販売記録'!$A$5:$A$1004,"<"&DATE(YEAR($A9),MONTH($A9)+1,1)) -> 0 | C9: =SUMIFS('販売記録'!$F$5:$F$1004,'販売記録'!$J$5:$J$1004,"販売済み",'販売記録'!$A$5:$A$1004,">="&$A9,'販売記録'!$A$5:$A$1004,"<"&DATE(YEAR($A9),MONTH($A9)+1,1)) -> 0 | D9: =SUMIFS('販売記録'!$G$5:$G$1004,'販売記録'!$J$5:$J$1004,"販売済み",'販売記録'!$A$5:$A$1004,">="&$A9,'販売記録'!$A$5:$A$1004,"<"&DATE(YEAR($A9),MONTH($A9)+1,1)) -> 0 | E9: =SUMIFS('販売記録'!$D$5:$D$1004,'販売記録'!$J$5:$J$1004,"販売済み",'販売記録'!$A$5:$A$1004,">="&$A9,'販売記録'!$A$5:$A$1004,"<"&DATE(YEAR($A9),MONTH($A9)+1,1)) -> 0 | F9: =SUMIFS('販売記録'!$H$5:$H$1004,'販売記録'!$J$5:$J$1004,"販売済み",'販売記録'!$A$5:$A$1004,">="&$A9,'販売記録'!$A$5:$A$1004,"<"&DATE(YEAR($A9),MONTH($A9)+1,1)) -> 0 | G9: =SUMIFS('販売記録'!$I$5:$I$1004,'販売記録'!$J$5:$J$1004,"販売済み",'販売記録'!$A$5:$A$1004,">="&$A9,'販売記録'!$A$5:$A$1004,"<"&DATE(YEAR($A9),MONTH($A9)+1,1)) -> 0
A10: =DATE($B$2,6,1) -> 46174 | B10: =SUMIFS('販売記録'!$E$5:$E$1004,'販売記録'!$J$5:$J$1004,"販売済み",'販売記録'!$A$5:$A$1004,">="&$A10,'販売記録'!$A$5:$A$1004,"<"&DATE(YEAR($A10),MONTH($A10)+1,1)) -> 0 | C10: =SUMIFS('販売記録'!$F$5:$F$1004,'販売記録'!$J$5:$J$1004,"販売済み",'販売記録'!$A$5:$A$1004,">="&$A10,'販売記録'!$A$5:$A$1004,"<"&DATE(YEAR($A10),MONTH($A10)+1,1)) -> 0 | D10: =SUMIFS('販売記録'!$G$5:$G$1004,'販売記録'!$J$5:$J$1004,"販売済み",'販売記録'!$A$5:$A$1004,">="&$A10,'販売記録'!$A$5:$A$1004,"<"&DATE(YEAR($A10),MONTH($A10)+1,1)) -> 0 | E10: =SUMIFS('販売記録'!$D$5:$D$1004,'販売記録'!$J$5:$J$1004,"販売済み",'販売記録'!$A$5:$A$1004,">="&$A10,'販売記録'!$A$5:$A$1004,"<"&DATE(YEAR($A10),MONTH($A10)+1,1)) -> 0 | F10: =SUMIFS('販売記録'!$H$5:$H$1004,'販売記録'!$J$5:$J$1004,"販売済み",'販売記録'!$A$5:$A$1004,">="&$A10,'販売記録'!$A$5:$A$1004,"<"&DATE(YEAR($A10),MONTH($A10)+1,1)) -> 0 | G10: =SUMIFS('販売記録'!$I$5:$I$1004,'販売記録'!$J$5:$J$1004,"販売済み",'販売記録'!$A$5:$A$1004,">="&$A10,'販売記録'!$A$5:$A$1004,"<"&DATE(YEAR($A10),MONTH($A10)+1,1)) -> 0
A11: =DATE($B$2,7,1) -> 46204 | B11: =SUMIFS('販売記録'!$E$5:$E$1004,'販売記録'!$J$5:$J$1004,"販売済み",'販売記録'!$A$5:$A$1004,">="&$A11,'販売記録'!$A$5:$A$1004,"<"&DATE(YEAR($A11),MONTH($A11)+1,1)) -> 0 | C11: =SUMIFS('販売記録'!$F$5:$F$1004,'販売記録'!$J$5:$J$1004,"販売済み",'販売記録'!$A$5:$A$1004,">="&$A11,'販売記録'!$A$5:$A$1004,"<"&DATE(YEAR($A11),MONTH($A11)+1,1)) -> 0 | D11: =SUMIFS('販売記録'!$G$5:$G$1004,'販売記録'!$J$5:$J$1004,"販売済み",'販売記録'!$A$5:$A$1004,">="&$A11,'販売記録'!$A$5:$A$1004,"<"&DATE(YEAR($A11),MONTH($A11)+1,1)) -> 0 | E11: =SUMIFS('販売記録'!$D$5:$D$1004,'販売記録'!$J$5:$J$1004,"販売済み",'販売記録'!$A$5:$A$1004,">="&$A11,'販売記録'!$A$5:$A$1004,"<"&DATE(YEAR($A11),MONTH($A11)+1,1)) -> 0 | F11: =SUMIFS('販売記録'!$H$5:$H$1004,'販売記録'!$J$5:$J$1004,"販売済み",'販売記録'!$A$5:$A$1004,">="&$A11,'販売記録'!$A$5:$A$1004,"<"&DATE(YEAR($A11),MONTH($A11)+1,1)) -> 0 | G11: =SUMIFS('販売記録'!$I$5:$I$1004,'販売記録'!$J$5:$J$1004,"販売済み",'販売記録'!$A$5:$A$1004,">="&$A11,'販売記録'!$A$5:$A$1004,"<"&DATE(YEAR($A11),MONTH($A11)+1,1)) -> 0
A12: =DATE($B$2,8,1) -> 46235 | B12: =SUMIFS('販売記録'!$E$5:$E$1004,'販売記録'!$J$5:$J$1004,"販売済み",'販売記録'!$A$5:$A$1004,">="&$A12,'販売記録'!$A$5:$A$1004,"<"&DATE(YEAR($A12),MONTH($A12)+1,1)) -> 0 | C12: =SUMIFS('販売記録'!$F$5:$F$1004,'販売記録'!$J$5:$J$1004,"販売済み",'販売記録'!$A$5:$A$1004,">="&$A12,'販売記録'!$A$5:$A$1004,"<"&DATE(YEAR($A12),MONTH($A12)+1,1)) -> 0 | D12: =SUMIFS('販売記録'!$G$5:$G$1004,'販売記録'!$J$5:$J$1004,"販売済み",'販売記録'!$A$5:$A$1004,">="&$A12,'販売記録'!$A$5:$A$1004,"<"&DATE(YEAR($A12),MONTH($A12)+1,1)) -> 0 | E12: =SUMIFS('販売記録'!$D$5:$D$1004,'販売記録'!$J$5:$J$1004,"販売済み",'販売記録'!$A$5:$A$1004,">="&$A12,'販売記録'!$A$5:$A$1004,"<"&DATE(YEAR($A12),MONTH($A12)+1,1)) -> 0 | F12: =SUMIFS('販売記録'!$H$5:$H$1004,'販売記録'!$J$5:$J$1004,"販売済み",'販売記録'!$A$5:$A$1004,">="&$A12,'販売記録'!$A$5:$A$1004,"<"&DATE(YEAR($A12),MONTH($A12)+1,1)) -> 0 | G12: =SUMIFS('販売記録'!$I$5:$I$1004,'販売記録'!$J$5:$J$1004,"販売済み",'販売記録'!$A$5:$A$1004,">="&$A12,'販売記録'!$A$5:$A$1004,"<"&DATE(YEAR($A12),MONTH($A12)+1,1)) -> 0
A13: =DATE($B$2,9,1) -> 46266 | B13: =SUMIFS('販売記録'!$E$5:$E$1004,'販売記録'!$J$5:$J$1004,"販売済み",'販売記録'!$A$5:$A$1004,">="&$A13,'販売記録'!$A$5:$A$1004,"<"&DATE(YEAR($A13),MONTH($A13)+1,1)) -> 0 | C13: =SUMIFS('販売記録'!$F$5:$F$1004,'販売記録'!$J$5:$J$1004,"販売済み",'販売記録'!$A$5:$A$1004,">="&$A13,'販売記録'!$A$5:$A$1004,"<"&DATE(YEAR($A13),MONTH($A13)+1,1)) -> 0 | D13: =SUMIFS('販売記録'!$G$5:$G$1004,'販売記録'!$J$5:$J$1004,"販売済み",'販売記録'!$A$5:$A$1004,">="&$A13,'販売記録'!$A$5:$A$1004,"<"&DATE(YEAR($A13),MONTH($A13)+1,1)) -> 0 | E13: =SUMIFS('販売記録'!$D$5:$D$1004,'販売記録'!$J$5:$J$1004,"販売済み",'販売記録'!$A$5:$A$1004,">="&$A13,'販売記録'!$A$5:$A$1004,"<"&DATE(YEAR($A13),MONTH($A13)+1,1)) -> 0 | F13: =SUMIFS('販売記録'!$H$5:$H$1004,'販売記録'!$J$5:$J$1004,"販売済み",'販売記録'!$A$5:$A$1004,">="&$A13,'販売記録'!$A$5:$A$1004,"<"&DATE(YEAR($A13),MONTH($A13)+1,1)) -> 0 | G13: =SUMIFS('販売記録'!$I$5:$I$1004,'販売記録'!$J$5:$J$1004,"販売済み",'販売記録'!$A$5:$A$1004,">="&$A13,'販売記録'!$A$5:$A$1004,"<"&DATE(YEAR($A13),MONTH($A13)+1,1)) -> 0
A14: =DATE($B$2,10,1) -> 46296 | B14: =SUMIFS('販売記録'!$E$5:$E$1004,'販売記録'!$J$5:$J$1004,"販売済み",'販売記録'!$A$5:$A$1004,">="&$A14,'販売記録'!$A$5:$A$1004,"<"&DATE(YEAR($A14),MONTH($A14)+1,1)) -> 6500 | C14: =SUMIFS('販売記録'!$F$5:$F$1004,'販売記録'!$J$5:$J$1004,"販売済み",'販売記録'!$A$5:$A$1004,">="&$A14,'販売記録'!$A$5:$A$1004,"<"&DATE(YEAR($A14),MONTH($A14)+1,1)) -> 650 | D14: =SUMIFS('販売記録'!$G$5:$G$1004,'販売記録'!$J$5:$J$1004,"販売済み",'販売記録'!$A$5:$A$1004,">="&$A14,'販売記録'!$A$5:$A$1004,"<"&DATE(YEAR($A14),MONTH($A14)+1,1)) -> 910 | E14: =SUMIFS('販売記録'!$D$5:$D$1004,'販売記録'!$J$5:$J$1004,"販売済み",'販売記録'!$A$5:$A$1004,">="&$A14,'販売記録'!$A$5:$A$1004,"<"&DATE(YEAR($A14),MONTH($A14)+1,1)) -> 2500 | F14: =SUMIFS('販売記録'!$H$5:$H$1004,'販売記録'!$J$5:$J$1004,"販売済み",'販売記録'!$A$5:$A$1004,">="&$A14,'販売記録'!$A$5:$A$1004,"<"&DATE(YEAR($A14),MONTH($A14)+1,1)) -> 150 | G14: =SUMIFS('販売記録'!$I$5:$I$1004,'販売記録'!$J$5:$J$1004,"販売済み",'販売記録'!$A$5:$A$1004,">="&$A14,'販売記録'!$A$5:$A$1004,"<"&DATE(YEAR($A14),MONTH($A14)+1,1)) -> 2290
A15: =DATE($B$2,11,1) -> 46327 | B15: =SUMIFS('販売記録'!$E$5:$E$1004,'販売記録'!$J$5:$J$1004,"販売済み",'販売記録'!$A$5:$A$1004,">="&$A15,'販売記録'!$A$5:$A$1004,"<"&DATE(YEAR($A15),MONTH($A15)+1,1)) -> 0 | C15: =SUMIFS('販売記録'!$F$5:$F$1004,'販売記録'!$J$5:$J$1004,"販売済み",'販売記録'!$A$5:$A$1004,">="&$A15,'販売記録'!$A$5:$A$1004,"<"&DATE(YEAR($A15),MONTH($A15)+1,1)) -> 0 | D15: =SUMIFS('販売記録'!$G$5:$G$1004,'販売記録'!$J$5:$J$1004,"販売済み",'販売記録'!$A$5:$A$1004,">="&$A15,'販売記録'!$A$5:$A$1004,"<"&DATE(YEAR($A15),MONTH($A15)+1,1)) -> 0 | E15: =SUMIFS('販売記録'!$D$5:$D$1004,'販売記録'!$J$5:$J$1004,"販売済み",'販売記録'!$A$5:$A$1004,">="&$A15,'販売記録'!$A$5:$A$1004,"<"&DATE(YEAR($A15),MONTH($A15)+1,1)) -> 0 | F15: =SUMIFS('販売記録'!$H$5:$H$1004,'販売記録'!$J$5:$J$1004,"販売済み",'販売記録'!$A$5:$A$1004,">="&$A15,'販売記録'!$A$5:$A$1004,"<"&DATE(YEAR($A15),MONTH($A15)+1,1)) -> 0 | G15: =SUMIFS('販売記録'!$I$5:$I$1004,'販売記録'!$J$5:$J$1004,"販売済み",'販売記録'!$A$5:$A$1004,">="&$A15,'販売記録'!$A$5:$A$1004,"<"&DATE(YEAR($A15),MONTH($A15)+1,1)) -> 0
A16: =DATE($B$2,12,1) -> 46357 | B16: =SUMIFS('販売記録'!$E$5:$E$1004,'販売記録'!$J$5:$J$1004,"販売済み",'販売記録'!$A$5:$A$1004,">="&$A16,'販売記録'!$A$5:$A$1004,"<"&DATE(YEAR($A16),MONTH($A16)+1,1)) -> 0 | C16: =SUMIFS('販売記録'!$F$5:$F$1004,'販売記録'!$J$5:$J$1004,"販売済み",'販売記録'!$A$5:$A$1004,">="&$A16,'販売記録'!$A$5:$A$1004,"<"&DATE(YEAR($A16),MONTH($A16)+1,1)) -> 0 | D16: =SUMIFS('販売記録'!$G$5:$G$1004,'販売記録'!$J$5:$J$1004,"販売済み",'販売記録'!$A$5:$A$1004,">="&$A16,'販売記録'!$A$5:$A$1004,"<"&DATE(YEAR($A16),MONTH($A16)+1,1)) -> 0 | E16: =SUMIFS('販売記録'!$D$5:$D$1004,'販売記録'!$J$5:$J$1004,"販売済み",'販売記録'!$A$5:$A$1004,">="&$A16,'販売記録'!$A$5:$A$1004,"<"&DATE(YEAR($A16),MONTH($A16)+1,1)) -> 0 | F16: =SUMIFS('販売記録'!$H$5:$H$1004,'販売記録'!$J$5:$J$1004,"販売済み",'販売記録'!$A$5:$A$1004,">="&$A16,'販売記録'!$A$5:$A$1004,"<"&DATE(YEAR($A16),MONTH($A16)+1,1)) -> 0 | G16: =SUMIFS('販売記録'!$I$5:$I$1004,'販売記録'!$J$5:$J$1004,"販売済み",'販売記録'!$A$5:$A$1004,">="&$A16,'販売記録'!$A$5:$A$1004,"<"&DATE(YEAR($A16),MONTH($A16)+1,1)) -> 0
A18: 年間合計 | B18: =SUM(B5:B16) -> 6500 | C18: =SUM(C5:C16) -> 650 | D18: =SUM(D5:D16) -> 910 | E18: =SUM(E5:E16) -> 2500 | F18: =SUM(F5:F16) -> 150 | G18: =SUM(G5:G16) -> 2290
